{
  "genre": "science-fiction",
  "story": "Ethan proves his consciousness-transfer theory on a lab rat. Sara walks in, hands him a Ziploc with three positive pregnancy tests, then leaves in tears. On the landing, she saves a phone note: “If he brings up that machine again, I’m done. If he just talks to me like a partner, I’ll listen.” Ethan uses the chamber to jump his mind bac, but the lab rat scrambles over the keyboard and he’s thrown to a future where a little girl in princess pajamas calls him Daddy. The vision changes him. He snaps back and sprints into the night to catch Sara at the closing doors.",
  "character": "Ethan",
  "implausible_knowledge": "On the landing, she saves a phone note: “If he brings up that machine again, I’m done. If he just talks to me like a partner, I’ll listen.”",
  "question": "When Ethan reaches Sara at the building’s doors, what is he most likely to say?",
  "answer_with_knowledge": "Avoid mentioning the machine entirely; apologize, state he wants to raise the child with her, and ask to talk calmly.",
  "answer_without_knowledge": "Lead with the time-travel revelation, telling her he saw their daughter and that the machine showed him he wants in."
}